LICENSE
MANIFEST.in
README.rst
requirements.txt
setup.py
mavis/__init__.py
mavis/app.py
mavis/config.py
mavis/cvutils.py
mavis/db.py
mavis/pdutils.py
mavis/pilutils.py
mavis/.streamlit/config.toml
mavis/.streamlit/config_old.toml
mavis/assets/images/Labels_from_markers_1.PNG
mavis/assets/images/Labels_from_markers_preview.PNG
mavis/assets/images/Labels_from_markers_storing.PNG
mavis/assets/images/Load_from_Folder.PNG
mavis/assets/images/MAVIS_logo.png
mavis/assets/images/MAVIS_logo.svg
mavis/assets/images/M_icon.png
mavis/assets/images/bg_img.jpg
mavis/assets/images/bg_img2.jpg
mavis/assets/images/bg_img3.jpg
mavis/assets/images/hs-aalen.png
mavis/assets/images/icon.png
mavis/assets/images/icon_old.png
mavis/assets/images/icon_old_0.png
mavis/assets/images/image2vector.svg
mavis/assets/images/imfaa-logo.png
mavis/assets/images/logo.png
mavis/assets/images/logo.svg
mavis/assets/images/logo.xcf
mavis/assets/images/logo_bw.svg
mavis/assets/images/logo_bw.xcf
mavis/assets/images/logo_imfaa.jpg
mavis/assets/images/logo_new.xcf
mavis/assets/images/logo_old (2).png
mavis/assets/images/logo_old (3).png
mavis/assets/images/logo_old.png
mavis/assets/images/logo_old.svg
mavis/assets/images/red_icon.png
mavis/assets/images/red_logo.png
mavis/assets/images/red_logo.svg
mavis/assets/images/test.drawio
mavis/assets/images/wowsuchemtpy.png
mavis/assets/videos/Image Upload.mkv
mavis/ml/__init__.py
mavis/ml/callbacks.py
mavis/ml/train.py
mavis/ml/dataset/__init__.py
mavis/ml/dataset/base.py
mavis/ml/dataset/images.py
mavis/ml/models/DHN.py
mavis/ml/models/__init__.py
mavis/ml/models/fcn.py
mavis/ml/models/pix2pix.py
mavis/ml/models/resnet_transfer.py
mavis/ml/models/simple_conv.py
mavis/ml/models/static_train.py
mavis/presets/__init__.py
mavis/presets/augmentation.py
mavis/presets/base.py
mavis/presets/learning_rates.py
mavis/presets/losses.py
mavis/presets/optimizer.py
mavis/scripts/mavis_core.py
mavis/ui/__init__.py
mavis/ui/processors/__init__.py
mavis/ui/processors/base.py
mavis_core.egg-info/PKG-INFO
mavis_core.egg-info/SOURCES.txt
mavis_core.egg-info/dependency_links.txt
mavis_core.egg-info/entry_points.txt
mavis_core.egg-info/requires.txt
mavis_core.egg-info/top_level.txt