Metadata-Version: 2.1
Name: mavis-core
Version: 0.5.5
Summary: Mavis - Machine Learning and Computer Vision. Turn code into applications.
Home-page: https://github.com/thetoby9944/mavis_core
Author: thetoby9944
Author-email: thetoby@web.de
License: UNKNOWN
Platform: UNKNOWN
Classifier: Development Status :: 4 - Beta
Classifier: Intended Audience :: Science/Research
Classifier: Intended Audience :: Developers
Classifier: Programming Language :: Python :: 3
Classifier: Programming Language :: Python :: 3.7
Classifier: Programming Language :: Python :: 3.8
Classifier: Programming Language :: Python :: 3.9
Classifier: License :: OSI Approved :: GNU Affero General Public License v3 or later (AGPLv3+)
License-File: LICENSE
